grgrjax/__init__.py
grgrjax/__version__.py
grgrjax/helpers.py
grgrjax/newton.py
grgrjax/test_all.py
grgrjax-0.4.7.dist-info/LICENSE
grgrjax-0.4.7.dist-info/METADATA
grgrjax-0.4.7.dist-info/WHEEL
grgrjax-0.4.7.dist-info/top_level.txt
grgrjax-0.4.7.dist-info/RECORD
