Metadata-Version: 2.2
Name: grgrjax
Version: 0.4.7
Summary: Some generic tools for JAX
Home-page: https://github.com/gboehl/grgrjax
Author: Gregor Boehl
Author-email: admin@gregorboehl.com
License: MIT
Classifier: License :: OSI Approved :: MIT License
Classifier: Programming Language :: Python :: 3
Classifier: Programming Language :: Python :: 3.10
License-File: LICENSE
Requires-Dist: jax
Requires-Dist: jaxlib
Dynamic: author
Dynamic: author-email
Dynamic: classifier
Dynamic: description
Dynamic: description-content-type
Dynamic: home-page
Dynamic: license
Dynamic: requires-dist
Dynamic: summary
